setup.cfg
setup.py
pgbackups/__init__.py
pgbackups/__main__.py
pgbackups/api.py
pgbackups/client.py
pgbackups/storage.py
pgbackups_py.egg-info/PKG-INFO
pgbackups_py.egg-info/SOURCES.txt
pgbackups_py.egg-info/dependency_links.txt
pgbackups_py.egg-info/entry_points.txt
pgbackups_py.egg-info/not-zip-safe
pgbackups_py.egg-info/requires.txt
pgbackups_py.egg-info/top_level.txt